<?xml version="1.0" encoding="utf-8" ?>
<dwsync>
<file name="btn_join_free.png" server="118.139.186.1" local="130422028515582501" remote="130422168000000000" Dst="0" />
<file name="mail-buyer-sent-contact_01.png" server="118.139.186.1" local="130351093495757502" remote="130421338200000000" Dst="0" />
<file name="divide_link.png" server="118.139.186.1" local="130422027876198749" remote="130421491200000000" Dst="0" />
<file name="product_img.jpg" server="118.139.186.1" local="130351093495757502" remote="130422168000000000" Dst="0" />
<file name="spacer.gif" server="118.139.186.1" local="130351093495767508" remote="130421338200000000" Dst="0" />
<file name="alert-email-product-pic-01.jpg" server="118.139.186.1" local="130371768779789159" remote="130421338200000000" Dst="0" />
<file name="alert-email-product-pic-03.jpg" server="118.139.186.1" local="130371768779799174" remote="130421338200000000" Dst="0" />
<file name="alert-email-product-pic-02.jpg" server="118.139.186.1" local="130371768779799174" remote="130421338200000000" Dst="0" />
<file name="alert-email-product-pic-04.jpg" server="118.139.186.1" local="130371768779809175" remote="130421338200000000" Dst="0" />
<file name="alert-email-product-pic-05.jpg" server="118.139.186.1" local="130371768779809175" remote="130421338200000000" Dst="0" />
<file name="alert-email-product-pic-06.jpg" server="118.139.186.1" local="130371768779819179" remote="130421338200000000" Dst="0" />
<file name="alert-email-product-pic-07.jpg" server="118.139.186.1" local="130371768779819179" remote="130421338200000000" Dst="0" />
<file name="alert-email-product-pic-08.jpg" server="118.139.186.1" local="130371768779819179" remote="130421338200000000" Dst="0" />
<file name="mail-alert-email-01.png" server="118.139.186.1" local="130422027561520198" remote="130422168000000000" Dst="0" />
<file name="mail-alert-arrow-icon-01.png" server="118.139.186.1" local="130371768779829185" remote="130421338200000000" Dst="0" />
<file name="mail-alert-email-09.png" server="118.139.186.1" local="130371768779839141" remote="130421338200000000" Dst="0" />
<file name="product_img.png" server="118.139.186.1" local="130422029907795180" remote="130421491200000000" Dst="0" />
</dwsync>